source_outbrain_amplify/__init__.py
source_outbrain_amplify/auth.py
source_outbrain_amplify/run.py
source_outbrain_amplify/schemas/budgets.json
source_outbrain_amplify/schemas/campaigns.json
source_outbrain_amplify/schemas/campaigns_geo_location.json
source_outbrain_amplify/schemas/marketers.json
source_outbrain_amplify/schemas/performance_promoted_links.json
source_outbrain_amplify/schemas/performance_report_campaigns_by_marketers.json
source_outbrain_amplify/schemas/performance_report_marketers_by_geo_performance.json
source_outbrain_amplify/schemas/performance_report_marketers_by_interest.json
source_outbrain_amplify/schemas/performance_report_marketers_by_platforms.json
source_outbrain_amplify/schemas/performance_report_marketers_by_publisher.json
source_outbrain_amplify/schemas/performance_report_marketers_campaigns_by_geo.json
source_outbrain_amplify/schemas/performance_report_marketers_campaigns_by_platforms.json
source_outbrain_amplify/schemas/performance_report_periodic_by_marketers.json
source_outbrain_amplify/schemas/performance_report_periodic_by_marketers_campaign.json
source_outbrain_amplify/schemas/performance_report_publishers_by_campaigns.json
source_outbrain_amplify/schemas/promoted_links.json
source_outbrain_amplify/schemas/promoted_links_sequence_for_campaigns.json
source_outbrain_amplify/source.py
source_outbrain_amplify/spec.yaml
airbyte_source_outbrain_amplify-0.2.21.dist-info/METADATA
airbyte_source_outbrain_amplify-0.2.21.dist-info/WHEEL
airbyte_source_outbrain_amplify-0.2.21.dist-info/entry_points.txt
airbyte_source_outbrain_amplify-0.2.21.dist-info/RECORD
