Metadata-Version: 2.1
Name: airbyte-source-outbrain-amplify
Version: 0.2.21
Summary: Source implementation for outbrain amplify.
Home-page: https://airbyte.com
License: ELv2
Author: Airbyte
Author-email: contact@airbyte.io
Requires-Python: >=3.9,<3.12
Classifier: License :: Other/Proprietary License
Classifier: Programming Language :: Python :: 3
Classifier: Programming Language :: Python :: 3.9
Classifier: Programming Language :: Python :: 3.10
Classifier: Programming Language :: Python :: 3.11
Requires-Dist: airbyte-cdk (==0.80.0)
Project-URL: Documentation, https://docs.airbyte.com/integrations/sources/outbrain-amplify
Project-URL: Repository, https://github.com/airbytehq/airbyte
